cspybase/__init__.py
cspybase/cli/__init__.py
cspybase/cli/core.py
cspybase/cli/gettoken.py
cspybase/cli/listalgorithms.py
cspybase/cli/listfiles.py
cspybase/cli/listjobs.py
cspybase/cli/listprojects.py
cspybase/cli/listusers.py
cspybase/cli/writecsvfileinproject.py
cspybase/services/__init__.py
cspybase/services/algorithm/__init__.py
cspybase/services/algorithm/access.py
cspybase/services/algorithm/algorithm.py
cspybase/services/algorithm/algorithmaction.py
cspybase/services/algorithm/algorithmconfiguration.py
cspybase/services/algorithm/algorithmgroup.py
cspybase/services/algorithm/algorithmparameter.py
cspybase/services/algorithm/algorithmversion.py
cspybase/services/core/__init__.py
cspybase/services/core/access.py
cspybase/services/core/connection.py
cspybase/services/core/exception.py
cspybase/services/core/object.py
cspybase/services/job/__init__.py
cspybase/services/job/access.py
cspybase/services/job/job.py
cspybase/services/project/__init__.py
cspybase/services/project/access.py
cspybase/services/project/file.py
cspybase/services/project/project.py
cspybase/services/user/__init__.py
cspybase/services/user/access.py
cspybase/services/user/user.py
cspybase-0.6.0.dist-info/METADATA
cspybase-0.6.0.dist-info/RECORD
cspybase-0.6.0.dist-info/WHEEL
cspybase-0.6.0.dist-info/entry_points.txt
cspybase-0.6.0.dist-info/top_level.txt
